README.rst
setup.py
compressor_celery/__init__.py
compressor_celery/tasks.py
compressor_celery/templatetags/__init__.py
compressor_celery/templatetags/compress_celery.py
django_compressor_celery.egg-info/PKG-INFO
django_compressor_celery.egg-info/SOURCES.txt
django_compressor_celery.egg-info/dependency_links.txt
django_compressor_celery.egg-info/not-zip-safe
django_compressor_celery.egg-info/requires.txt
django_compressor_celery.egg-info/top_level.txt