Metadata-Version: 1.1
Name: django-compressor-celery
Version: 0.2
Summary: Integrate django_compressor with celery
Home-page: http://github.com/jarus/django_compressor_celery/
Author: Christoph Heer
Author-email: christoph@thelabmill.de
License: MIT
Platform: UNKNOWN
Classifier: Development Status :: 4 - Beta
Classifier: Framework :: Django
Classifier: Intended Audience :: Developers
Classifier: License :: OSI Approved :: MIT License
Classifier: Operating System :: OS Independent
Classifier: Programming Language :: Python
Classifier: Programming Language :: Python :: 2.6
Classifier: Programming Language :: Python :: 2.7
Classifier: Topic :: Internet :: WWW/HTTP
